topsis_vansh_102353012/__init__.py
topsis_vansh_102353012/topsis.py
topsis_vansh_102353012-1.0.1.dist-info/METADATA
topsis_vansh_102353012-1.0.1.dist-info/WHEEL
topsis_vansh_102353012-1.0.1.dist-info/entry_points.txt
topsis_vansh_102353012-1.0.1.dist-info/top_level.txt
topsis_vansh_102353012-1.0.1.dist-info/RECORD
